relayx_py/__init__.py
relayx_py/kv_storage.py
relayx_py/queue.py
relayx_py/realtime.py
relayx_py/utils.py
relayx_py/models/__init__.py
relayx_py/models/message.py
relayx_py/tests/__init__.py
relayx_py/tests/test.py
relayx_py/tests/test_kv_storage.py
relayx_py/tests/test_queue.py
relayx_py-1.1.0.dist-info/licenses/LICENSE
relayx_py-1.1.0.dist-info/METADATA
relayx_py-1.1.0.dist-info/WHEEL
relayx_py-1.1.0.dist-info/top_level.txt
relayx_py-1.1.0.dist-info/RECORD
