Metadata-Version: 2.4
Name: relayx_py
Version: 1.1.0
Summary: A powerful library for integrating real-time communication into your software stack, powered by the Relay Network.
Author: Relay
License: Apache 2.0
License-File: LICENSE
Requires-Dist: nats-py==2.12.0
Requires-Dist: pytest-asyncio==1.0.0
Requires-Dist: nkeys==0.2.1
Requires-Dist: msgpack==1.1.1
Requires-Dist: tzlocal==5.3.1
Requires-Dist: tabulate==0.9.0
Dynamic: author
Dynamic: description
Dynamic: description-content-type
Dynamic: license
Dynamic: license-file
Dynamic: requires-dist
Dynamic: summary
